liblaf/pytest_preset/__init__.py
liblaf/pytest_preset/__init__.pyi
liblaf/pytest_preset/_version.py
liblaf/pytest_preset/_version.pyi
liblaf/pytest_preset/py.typed
liblaf_pytest_preset-0.1.3.dist-info/METADATA
liblaf_pytest_preset-0.1.3.dist-info/WHEEL
liblaf_pytest_preset-0.1.3.dist-info/licenses/LICENSE
liblaf_pytest_preset-0.1.3.dist-info/RECORD
