Metadata-Version: 2.4
Name: liblaf-pytest-preset
Version: 0.1.3
Project-URL: Changelog, https://github.com/liblaf/pytest-preset/blob/main/CHANGELOG.md
Project-URL: Documentation, https://liblaf.github.io/pytest-preset/
Project-URL: Funding, https://github.com/liblaf/pytest-preset?sponsor=1
Project-URL: Homepage, https://github.com/liblaf/pytest-preset
Project-URL: Issue Tracker, https://github.com/liblaf/pytest-preset/issues
Project-URL: Release Notes, https://github.com/liblaf/pytest-preset/releases
Project-URL: Source Code, https://github.com/liblaf/pytest-preset
Author-email: liblaf <30631553+liblaf@users.noreply.github.com>
License-Expression: MIT
License-File: LICENSE
Classifier: Development Status :: 4 - Beta
Classifier: Intended Audience :: Developers
Classifier: License :: OSI Approved
Classifier: License :: OSI Approved :: MIT License
Classifier: Operating System :: OS Independent
Classifier: Programming Language :: Python
Classifier: Programming Language :: Python :: 3
Classifier: Programming Language :: Python :: 3.12
Classifier: Programming Language :: Python :: 3.13
Classifier: Programming Language :: Python :: 3.14
Classifier: Typing :: Typed
Requires-Python: >=3.12
Requires-Dist: hypothesis<7,>=6
Requires-Dist: pytest-codspeed<5,>=4
Requires-Dist: pytest-cov<8,>=7
Requires-Dist: pytest-randomly<5,>=4
Requires-Dist: pytest-xdist<4,>=3
Requires-Dist: pytest<10,>=9
